libzrod/__init__.py
libzrod/_libzrod.py
libzrod/demo.py
libzrod/libzrod.cpython-38-x86_64-linux-gnu.so
libzrod.libs/libbrotlicommon-6ce2a53c.so.1.0.6
libzrod.libs/libbrotlidec-811d1be3.so.1.0.6
libzrod.libs/libcom_err-448cbf49.so.2.1
libzrod.libs/libcrypt-52aca757.so.1.1.0
libzrod.libs/libcrypto-bdaed0ea.so.1.1.1k
libzrod.libs/libcurl-c96f124b.so.4.5.0
libzrod.libs/libgssapi_krb5-323bbd21.so.2.2
libzrod.libs/libidn2-2f4a5893.so.0.3.6
libzrod.libs/libk5crypto-9a74ff38.so.3.1
libzrod.libs/libkeyutils-2777d33d.so.1.6
libzrod.libs/libkrb5-a55300e8.so.3.3
libzrod.libs/libkrb5support-e6594cfc.so.0.1
libzrod.libs/liblber-2-d20824ef.4.so.2.10.9
libzrod.libs/libldap-2-cea2a960.4.so.2.10.9
libzrod.libs/libnghttp2-39367a22.so.14.17.0
libzrod.libs/libpcre2-8-516f4c9d.so.0.7.1
libzrod.libs/libpsl-99becdd3.so.5.3.1
libzrod.libs/libsasl2-7de4d792.so.3.0.0
libzrod.libs/libselinux-d0805dcb.so.1
libzrod.libs/libssh-c11d285b.so.4.8.7
libzrod.libs/libssl-60250281.so.1.1.1k
libzrod.libs/libunistring-05abdd40.so.2.1.0
libzrod-0.1.23.dist-info/METADATA
libzrod-0.1.23.dist-info/WHEEL
libzrod-0.1.23.dist-info/RECORD
