Metadata-Version: 2.4
Name: libzrod
Version: 0.1.23
Summary: Sucker Rod Design Library
Keywords: zrod,srod,qrod,rodstar,rod pump,rod design,rod lift,sucker rod,gibbs,everitt jennings,petroleum,oil well,pumpjack,sucker rod,wave equation
Author-Email: Walter Phillips <dev@zrod.io>
License-Expression: LicenseRef-Commercial
Classifier: Development Status :: 4 - Beta
Classifier: Programming Language :: C
Classifier: Programming Language :: C++
Classifier: Programming Language :: Python
Classifier: Intended Audience :: Developers
Classifier: Intended Audience :: Science/Research
Classifier: Topic :: Scientific/Engineering :: Mathematics
Classifier: Topic :: Scientific/Engineering :: Physics
Classifier: Topic :: Scientific/Engineering :: Information Analysis
